vital_agent_kg_utils/__init__.py
vital_agent_kg_utils/diffbot_client/__init__.py
vital_agent_kg_utils/diffbot_client/diffbot_client.py
vital_agent_kg_utils/kgraphutils/__init__.py
vital_agent_kg_utils/kgraphutils/kgraph_utils.py
vital_agent_kg_utils/kgservice_manager/__init__.py
vital_agent_kg_utils/kgservice_manager/kgraphservice_manager.py
vital_agent_kg_utils/vital_agent_rest_client/__init__.py
vital_agent_kg_utils/vital_agent_rest_client/vital_agent_rest_client.py
vital_agent_kg_utils/vital_agent_rest_resource_client/__init__.py
vital_agent_kg_utils/vital_agent_rest_resource_client/tool_service_interface.py
vital_agent_kg_utils/vital_agent_rest_resource_client/vital_agent_rest_resource_client.py
vital_agent_kg_utils/vital_agent_rest_resource_client/tools/__init__.py
vital_agent_kg_utils/vital_agent_rest_resource_client/tools/tool_data.py
vital_agent_kg_utils/vital_agent_rest_resource_client/tools/tool_handler.py
vital_agent_kg_utils/vital_agent_rest_resource_client/tools/tool_name_enum.py
vital_agent_kg_utils/vital_agent_rest_resource_client/tools/tool_parameters.py
vital_agent_kg_utils/vital_agent_rest_resource_client/tools/tool_request.py
vital_agent_kg_utils/vital_agent_rest_resource_client/tools/tool_response.py
vital_agent_kg_utils/vital_agent_rest_resource_client/tools/tool_results.py
vital_agent_kg_utils/vital_agent_rest_resource_client/tools/amazon_shopping/__init__.py
vital_agent_kg_utils/vital_agent_rest_resource_client/tools/amazon_shopping/amazon_product_search_request.py
vital_agent_kg_utils/vital_agent_rest_resource_client/tools/amazon_shopping/amazon_product_search_response.py
vital_agent_kg_utils/vital_agent_rest_resource_client/tools/amazon_shopping/amazon_product_search_tool_handler.py
vital_agent_kg_utils/vital_agent_rest_resource_client/tools/amazon_shopping/amazon_shopping_request.py
vital_agent_kg_utils/vital_agent_rest_resource_client/tools/amazon_shopping/amazon_shopping_response.py
vital_agent_kg_utils-0.1.7.dist-info/LICENSE
vital_agent_kg_utils-0.1.7.dist-info/METADATA
vital_agent_kg_utils-0.1.7.dist-info/WHEEL
vital_agent_kg_utils-0.1.7.dist-info/top_level.txt
vital_agent_kg_utils-0.1.7.dist-info/RECORD
